pyclui/__init__.py
pyclui/clui.py
pyclui/pytransform/__init__.py
pyclui/pytransform/platforms/linux/aarch64/_pytransform.so
pyclui/pytransform/platforms/linux/x86_64/_pytransform.so
pyclui-0.0.17.dist-info/LICENSE.txt
pyclui-0.0.17.dist-info/METADATA
pyclui-0.0.17.dist-info/WHEEL
pyclui-0.0.17.dist-info/top_level.txt
pyclui-0.0.17.dist-info/RECORD
