Metadata-Version: 2.1
Name: pyclui
Version: 0.0.17
Summary: Command Line UI Utilities for Python
Home-page: https://pypi.org/project/pyclui
Author: Cibo
Author-email: cibo@bio-electric.com
License: Proprietary
Platform: UNKNOWN
Classifier: Operating System :: POSIX :: Linux
Classifier: Programming Language :: Python :: 3
Classifier: Programming Language :: Python :: 3 :: Only
Classifier: Programming Language :: Python :: 3.10
Classifier: License :: Other/Proprietary License
Requires-Python: ==3.10.*
License-File: LICENSE.txt
